pyparseit/__init__.py
pyparseit/cli.py
pyparseit/code_snippet.py
pyparseit/exceptions.py
pyparseit/parser.py
pyparseit/utils.py
pyparseit-0.2.0.dist-info/LICENSE
pyparseit-0.2.0.dist-info/METADATA
pyparseit-0.2.0.dist-info/WHEEL
pyparseit-0.2.0.dist-info/entry_points.txt
pyparseit-0.2.0.dist-info/top_level.txt
pyparseit-0.2.0.dist-info/RECORD
