Metadata-Version: 2.1
Name: pyparseit
Version: 0.2.0
Summary: A library to parse Markdown and extract code snippets
Home-page: https://github.com/uladkaminski/pyparseit
Author: uladkaminski
Author-email: i@uladkaminski.com
Classifier: Programming Language :: Python :: 3
Classifier: License :: OSI Approved :: MIT License
Classifier: Operating System :: OS Independent
License-File: LICENSE
